mdBuilder/MdBuilder.py
mdBuilder/__init__.py
mdElement/__init__.py
mdElement/element.py
mdElement/block/__init__.py
mdElement/block/blockquote.py
mdElement/block/fencedcodeblock.py
mdElement/block/frontmatter.py
mdElement/block/heading.py
mdElement/block/horizontalrule.py
mdElement/block/image.py
mdElement/block/link.py
mdElement/block/list.py
mdElement/block/paragraph.py
mdElement/block/table.py
mdElement/inline/__init__.py
mdElement/inline/code.py
mdElement/inline/emphasis.py
mdElement/inline/strikethrough.py
mdBuilder-1.0.7.dist-info/LICENSE
mdBuilder-1.0.7.dist-info/METADATA
mdBuilder-1.0.7.dist-info/WHEEL
mdBuilder-1.0.7.dist-info/top_level.txt
mdBuilder-1.0.7.dist-info/RECORD
